zdppy_grpc/__init__.py
zdppy_grpc/grpc.py
zdppy_grpc/health/__init__.py
zdppy_grpc/health/v1/__init__.py
zdppy_grpc/health/v1/_async.py
zdppy_grpc/health/v1/health.py
zdppy_grpc/health/v1/health_pb2.py
zdppy_grpc/health/v1/health_pb2_grpc.py
zdppy_grpc-0.1.0.dist-info/LICENSE
zdppy_grpc-0.1.0.dist-info/WHEEL
zdppy_grpc-0.1.0.dist-info/METADATA
zdppy_grpc-0.1.0.dist-info/RECORD
